{"apiName":"Product2","associateEntityType":null,"associateParentEntity":null,"childRelationships":[{"childObjectApiName":"ActivityHistory","fieldName":"WhatId","junctionIdListNames":[],"junctionReferenceTo":[],"relationshipName":"ActivityHistories"},{"childObjectApiName":"ApprovalSubmission","fieldName":"RelatedRecordId","junctionIdListNames":[],"junctionReferenceTo":[],"relationshipName":"ApprovalSubmissions"},{"childObjectApiName":"ApprovalWorkItem","fieldName":"RelatedRecordId","junctionIdListNames":[],"junctionReferenceTo":[],"relationshipName":"ApprovalWorkItems"},{"childObjectApiName":"Asset","fieldName":"Product2Id","junctionIdListNames":[],"junctionReferenceTo":[],"relationshipName":"Assets"},{"childObjectApiName":"AttachedContentDocument","fieldName":"LinkedEntityId","junctionIdListNames":[],"junctionReferenceTo":[],"relationshipName":"AttachedContentDocuments"},{"childObjectApiName":"Attachment","fieldName":"ParentId","junctionIdListNames":[],"junctionReferenceTo":[],"relationshipName":"Attachments"},{"childObjectApiName":"CombinedAttachment","fieldName":"ParentId","junctionIdListNames":[],"junctionReferenceTo":[],"relationshipName":"CombinedAttachments"},{"childObjectApiName":"ContentDocumentLink","fieldName":"LinkedEntityId","junctionIdListNames":[],"junctionReferenceTo":[],"relationshipName":"ContentDocumentLinks"},{"childObjectApiName":"EmailMessage","fieldName":"RelatedToId","junctionIdListNames":[],"junctionReferenceTo":[],"relationshipName":"Emails"},{"childObjectApiName":"EntitySubscription","fieldName":"ParentId","junctionIdListNames":[],"junctionReferenceTo":[],"relationshipName":"FeedSubscriptionsForEntity"},{"childObjectApiName":"Event","fieldName":"WhatId","junctionIdListNames":[],"junctionReferenceTo":[],"relationshipName":"Events"},{"childObjectApiName":"FlowOrchestrationWorkItem","fieldName":"RelatedRecordId","junctionIdListNames":[],"junctionReferenceTo":[],"relationshipName":"FlowOrchestrationWorkItems"},{"childObjectApiName":"ListEmail","fieldName":"RelatedToId","junctionIdListNames":[],"junctionReferenceTo":[],"relationshipName":"ListEmails"},{"childObjectApiName":"Note","fieldName":"ParentId","junctionIdListNames":[],"junctionReferenceTo":[],"relationshipName":"Notes"},{"childObjectApiName":"NoteAndAttachment","fieldName":"ParentId","junctionIdListNames":[],"junctionReferenceTo":[],"relationshipName":"NotesAndAttachments"},{"childObjectApiName":"OpenActivity","fieldName":"WhatId","junctionIdListNames":[],"junctionReferenceTo":[],"relationshipName":"OpenActivities"},{"childObjectApiName":"PricebookEntry","fieldName":"Product2Id","junctionIdListNames":[],"junctionReferenceTo":[],"relationshipName":"PricebookEntries"},{"childObjectApiName":"ProcessInstance","fieldName":"TargetObjectId","junctionIdListNames":[],"junctionReferenceTo":[],"relationshipName":"ProcessInstances"},{"childObjectApiName":"ProcessInstanceHistory","fieldName":"TargetObjectId","junctionIdListNames":[],"junctionReferenceTo":[],"relationshipName":"ProcessSteps"},{"childObjectApiName":"Product2Feed","fieldName":"ParentId","junctionIdListNames":[],"junctionReferenceTo":[],"relationshipName":"Feeds"},{"childObjectApiName":"Product2History","fieldName":"Product2Id","junctionIdListNames":[],"junctionReferenceTo":[],"relationshipName":"Histories"},{"childObjectApiName":"ProductConsumed","fieldName":"Product2Id","junctionIdListNames":[],"junctionReferenceTo":[],"relationshipName":"ProductsConsumed"},{"childObjectApiName":"ProductItem","fieldName":"Product2Id","junctionIdListNames":[],"junctionReferenceTo":[],"relationshipName":"ProductItems"},{"childObjectApiName":"ProductRequestLineItem","fieldName":"Product2Id","junctionIdListNames":[],"junctionReferenceTo":[],"relationshipName":"ProductRequestLineItems"},{"childObjectApiName":"ProductRequired","fieldName":"Product2Id","junctionIdListNames":[],"junctionReferenceTo":[],"relationshipName":"ProductsRequired"},{"childObjectApiName":"ProductServiceCampaign","fieldName":"Product2Id","junctionIdListNames":[],"junctionReferenceTo":[],"relationshipName":"ProductServiceCampaignProducts"},{"childObjectApiName":"ProductServiceCampaignItem","fieldName":"Product2Id","junctionIdListNames":[],"junctionReferenceTo":[],"relationshipName":"ProductServiceCampaignItems"},{"childObjectApiName":"ProductTransfer","fieldName":"Product2Id","junctionIdListNames":[],"junctionReferenceTo":[],"relationshipName":"ProductTransfers"},{"childObjectApiName":"ProductWarrantyTerm","fieldName":"CoveredProductId","junctionIdListNames":[],"junctionReferenceTo":[],"relationshipName":"ProductWarrantyTermProducts"},{"childObjectApiName":"RecordAction","fieldName":"RecordId","junctionIdListNames":[],"junctionReferenceTo":[],"relationshipName":"RecordActions"},{"childObjectApiName":"RecordActionHistory","fieldName":"ParentRecordId","junctionIdListNames":[],"junctionReferenceTo":[],"relationshipName":"RecordActionHistories"},{"childObjectApiName":"ReturnOrderLineItem","fieldName":"Product2Id","junctionIdListNames":[],"junctionReferenceTo":[],"relationshipName":"ReturnOrderLineItems"},{"childObjectApiName":"SerializedProduct","fieldName":"Product2Id","junctionIdListNames":[],"junctionReferenceTo":[],"relationshipName":"SerializedProducts"},{"childObjectApiName":"ShipmentItem","fieldName":"Product2Id","junctionIdListNames":[],"junctionReferenceTo":[],"relationshipName":"ShipmentItems"},{"childObjectApiName":"Task","fieldName":"WhatId","junctionIdListNames":[],"junctionReferenceTo":[],"relationshipName":"Tasks"},{"childObjectApiName":"WorkOrderLineItem","fieldName":"Product2Id","junctionIdListNames":[],"junctionReferenceTo":[],"relationshipName":"WorkOrderLineItems"},{"childObjectApiName":"WorkPlanSelectionRule","fieldName":"Product2Id","junctionIdListNames":[],"junctionReferenceTo":[],"relationshipName":"WorkPlanSelectionRules"}],"compactLayoutable":true,"createable":true,"custom":false,"defaultRecordTypeId":"012000000000000AAA","deletable":true,"dependentFields":{},"eTag":"1e0a1bf7f397e245fcea6efea0c3d1e6","feedEnabled":false,"fields":{"CloneSourceId":{"apiName":"CloneSourceId","calculated":false,"compound":false,"compoundComponentName":null,"compoundFieldName":null,"controllerName":null,"controllingFields":[],"createable":false,"custom":false,"dataType":"Reference","externalId":false,"extraTypeInfo":null,"filterable":true,"filteredLookupInfo":null,"highScaleNumber":false,"htmlFormatted":false,"inlineHelpText":null,"label":"Clone Source","length":18,"maskType":null,"nameField":false,"polymorphicForeignKey":false,"precision":0,"reference":true,"referenceTargetField":null,"referenceToInfos":[],"relationshipName":null,"required":false,"scale":0,"searchPrefilterable":false,"sortable":true,"unique":false,"updateable":false},"CreatedById":{"apiName":"CreatedById","calculated":false,"compound":false,"compoundComponentName":null,"compoundFieldName":null,"controllerName":null,"controllingFields":[],"createable":false,"custom":false,"dataType":"Reference","externalId":false,"extraTypeInfo":null,"filterable":true,"filteredLookupInfo":null,"highScaleNumber":false,"htmlFormatted":false,"inlineHelpText":null,"label":"Created By ID","length":18,"maskType":null,"nameField":false,"polymorphicForeignKey":false,"precision":0,"reference":true,"referenceTargetField":null,"referenceToInfos":[{"apiName":"User","nameFields":["FirstName","LastName","Name"]}],"relationshipName":"CreatedBy","required":true,"scale":0,"searchPrefilterable":false,"sortable":true,"unique":false,"updateable":false},"CreatedDate":{"apiName":"CreatedDate","calculated":false,"compound":false,"compoundComponentName":null,"compoundFieldName":null,"controllerName":null,"controllingFields":[],"createable":false,"custom":false,"dataType":"DateTime","externalId":false,"extraTypeInfo":null,"filterable":true,"filteredLookupInfo":null,"highScaleNumber":false,"htmlFormatted":false,"inlineHelpText":null,"label":"Created Date","length":0,"maskType":null,"nameField":false,"polymorphicForeignKey":false,"precision":0,"reference":false,"referenceTargetField":null,"referenceToInfos":[],"relationshipName":null,"required":true,"scale":0,"searchPrefilterable":false,"sortable":true,"unique":false,"updateable":false},"CurrencyIsoCode":{"apiName":"CurrencyIsoCode","calculated":false,"compound":false,"compoundComponentName":null,"compoundFieldName":null,"controllerName":null,"controllingFields":[],"createable":true,"custom":false,"dataType":"Picklist","externalId":false,"extraTypeInfo":null,"filterable":true,"filteredLookupInfo":null,"highScaleNumber":false,"htmlFormatted":false,"inlineHelpText":null,"label":"Currency ISO Code","length":3,"maskType":null,"nameField":false,"polymorphicForeignKey":false,"precision":0,"reference":false,"referenceTargetField":null,"referenceToInfos":[],"relationshipName":null,"required":true,"scale":0,"searchPrefilterable":false,"sortable":true,"unique":false,"updateable":true},"Description":{"apiName":"Description","calculated":false,"compound":false,"compoundComponentName":null,"compoundFieldName":null,"controllerName":null,"controllingFields":[],"createable":true,"custom":false,"dataType":"TextArea","externalId":false,"extraTypeInfo":"PlainTextArea","filterable":true,"filteredLookupInfo":null,"highScaleNumber":false,"htmlFormatted":false,"inlineHelpText":null,"label":"Product Description","length":4000,"maskType":null,"nameField":false,"polymorphicForeignKey":false,"precision":0,"reference":false,"referenceTargetField":null,"referenceToInfos":[],"relationshipName":null,"required":false,"scale":0,"searchPrefilterable":false,"sortable":true,"unique":false,"updateable":true},"DisplayUrl":{"apiName":"DisplayUrl","calculated":false,"compound":false,"compoundComponentName":null,"compoundFieldName":null,"controllerName":null,"controllingFields":[],"createable":true,"custom":false,"dataType":"Url","externalId":false,"extraTypeInfo":null,"filterable":true,"filteredLookupInfo":null,"highScaleNumber":false,"htmlFormatted":false,"inlineHelpText":null,"label":"Display URL","length":1000,"maskType":null,"nameField":false,"polymorphicForeignKey":false,"precision":0,"reference":false,"referenceTargetField":null,"referenceToInfos":[],"relationshipName":null,"required":false,"scale":0,"searchPrefilterable":false,"sortable":true,"unique":false,"updateable":true},"ExternalDataSourceId":{"apiName":"ExternalDataSourceId","calculated":false,"compound":false,"compoundComponentName":null,"compoundFieldName":null,"controllerName":null,"controllingFields":[],"createable":true,"custom":false,"dataType":"Reference","externalId":false,"extraTypeInfo":null,"filterable":true,"filteredLookupInfo":null,"highScaleNumber":false,"htmlFormatted":false,"inlineHelpText":null,"label":"External Data Source ID","length":18,"maskType":null,"nameField":false,"polymorphicForeignKey":false,"precision":0,"reference":true,"referenceTargetField":null,"referenceToInfos":[{"apiName":"ExternalDataSource","nameFields":["DeveloperName"]}],"relationshipName":null,"required":false,"scale":0,"searchPrefilterable":false,"sortable":true,"unique":false,"updateable":true},"ExternalId":{"apiName":"ExternalId","calculated":false,"compound":false,"compoundComponentName":null,"compoundFieldName":null,"controllerName":null,"controllingFields":[],"createable":true,"custom":false,"dataType":"String","externalId":false,"extraTypeInfo":null,"filterable":true,"filteredLookupInfo":null,"highScaleNumber":false,"htmlFormatted":false,"inlineHelpText":null,"label":"External ID","length":255,"maskType":null,"nameField":false,"polymorphicForeignKey":false,"precision":0,"reference":false,"referenceTargetField":null,"referenceToInfos":[],"relationshipName":null,"required":false,"scale":0,"searchPrefilterable":false,"sortable":true,"unique":false,"updateable":true},"Family":{"apiName":"Family","calculated":false,"compound":false,"compoundComponentName":null,"compoundFieldName":null,"controllerName":null,"controllingFields":[],"createable":true,"custom":false,"dataType":"Picklist","externalId":false,"extraTypeInfo":null,"filterable":true,"filteredLookupInfo":null,"highScaleNumber":false,"htmlFormatted":false,"inlineHelpText":null,"label":"Product Family","length":255,"maskType":null,"nameField":false,"polymorphicForeignKey":false,"precision":0,"reference":false,"referenceTargetField":null,"referenceToInfos":[],"relationshipName":null,"required":false,"scale":0,"searchPrefilterable":false,"sortable":true,"unique":false,"updateable":true},"Id":{"apiName":"Id","calculated":false,"compound":false,"compoundComponentName":null,"compoundFieldName":null,"controllerName":null,"controllingFields":[],"createable":false,"custom":false,"dataType":"String","externalId":false,"extraTypeInfo":null,"filterable":true,"filteredLookupInfo":null,"highScaleNumber":false,"htmlFormatted":false,"inlineHelpText":null,"label":"Product ID","length":18,"maskType":null,"nameField":false,"polymorphicForeignKey":false,"precision":0,"reference":false,"referenceTargetField":null,"referenceToInfos":[],"relationshipName":null,"required":true,"scale":0,"searchPrefilterable":false,"sortable":true,"unique":false,"updateable":false},"IsActive":{"apiName":"IsActive","calculated":false,"compound":false,"compoundComponentName":null,"compoundFieldName":null,"controllerName":null,"controllingFields":[],"createable":true,"custom":false,"dataType":"Boolean","externalId":false,"extraTypeInfo":null,"filterable":true,"filteredLookupInfo":null,"highScaleNumber":false,"htmlFormatted":false,"inlineHelpText":null,"label":"Active","length":0,"maskType":null,"nameField":false,"polymorphicForeignKey":false,"precision":0,"reference":false,"referenceTargetField":null,"referenceToInfos":[],"relationshipName":null,"required":true,"scale":0,"searchPrefilterable":false,"sortable":true,"unique":false,"updateable":true},"IsArchived":{"apiName":"IsArchived","calculated":false,"compound":false,"compoundComponentName":null,"compoundFieldName":null,"controllerName":null,"controllingFields":[],"createable":false,"custom":false,"dataType":"Boolean","externalId":false,"extraTypeInfo":null,"filterable":true,"filteredLookupInfo":null,"highScaleNumber":false,"htmlFormatted":false,"inlineHelpText":null,"label":"Archived","length":0,"maskType":null,"nameField":false,"polymorphicForeignKey":false,"precision":0,"reference":false,"referenceTargetField":null,"referenceToInfos":[],"relationshipName":null,"required":true,"scale":0,"searchPrefilterable":false,"sortable":true,"unique":false,"updateable":false},"IsDeleted":{"apiName":"IsDeleted","calculated":false,"compound":false,"compoundComponentName":null,"compoundFieldName":null,"controllerName":null,"controllingFields":[],"createable":false,"custom":false,"dataType":"Boolean","externalId":false,"extraTypeInfo":null,"filterable":true,"filteredLookupInfo":null,"highScaleNumber":false,"htmlFormatted":false,"inlineHelpText":null,"label":"Deleted","length":0,"maskType":null,"nameField":false,"polymorphicForeignKey":false,"precision":0,"reference":false,"referenceTargetField":null,"referenceToInfos":[],"relationshipName":null,"required":true,"scale":0,"searchPrefilterable":false,"sortable":true,"unique":false,"updateable":false},"IsSerialized":{"apiName":"IsSerialized","calculated":false,"compound":false,"compoundComponentName":null,"compoundFieldName":null,"controllerName":null,"controllingFields":[],"createable":true,"custom":false,"dataType":"Boolean","externalId":false,"extraTypeInfo":null,"filterable":true,"filteredLookupInfo":null,"highScaleNumber":false,"htmlFormatted":false,"inlineHelpText":null,"label":"Serialized","length":0,"maskType":null,"nameField":false,"polymorphicForeignKey":false,"precision":0,"reference":false,"referenceTargetField":null,"referenceToInfos":[],"relationshipName":null,"required":true,"scale":0,"searchPrefilterable":false,"sortable":true,"unique":false,"updateable":true},"LastModifiedById":{"apiName":"LastModifiedById","calculated":false,"compound":false,"compoundComponentName":null,"compoundFieldName":null,"controllerName":null,"controllingFields":[],"createable":false,"custom":false,"dataType":"Reference","externalId":false,"extraTypeInfo":null,"filterable":true,"filteredLookupInfo":null,"highScaleNumber":false,"htmlFormatted":false,"inlineHelpText":null,"label":"Last Modified By ID","length":18,"maskType":null,"nameField":false,"polymorphicForeignKey":false,"precision":0,"reference":true,"referenceTargetField":null,"referenceToInfos":[{"apiName":"User","nameFields":["FirstName","LastName","Name"]}],"relationshipName":"LastModifiedBy","required":true,"scale":0,"searchPrefilterable":false,"sortable":true,"unique":false,"updateable":false},"LastModifiedDate":{"apiName":"LastModifiedDate","calculated":false,"compound":false,"compoundComponentName":null,"compoundFieldName":null,"controllerName":null,"controllingFields":[],"createable":false,"custom":false,"dataType":"DateTime","externalId":false,"extraTypeInfo":null,"filterable":true,"filteredLookupInfo":null,"highScaleNumber":false,"htmlFormatted":false,"inlineHelpText":null,"label":"Last Modified Date","length":0,"maskType":null,"nameField":false,"polymorphicForeignKey":false,"precision":0,"reference":false,"referenceTargetField":null,"referenceToInfos":[],"relationshipName":null,"required":true,"scale":0,"searchPrefilterable":false,"sortable":true,"unique":false,"updateable":false},"LastReferencedDate":{"apiName":"LastReferencedDate","calculated":false,"compound":false,"compoundComponentName":null,"compoundFieldName":null,"controllerName":null,"controllingFields":[],"createable":false,"custom":false,"dataType":"DateTime","externalId":false,"extraTypeInfo":null,"filterable":true,"filteredLookupInfo":null,"highScaleNumber":false,"htmlFormatted":false,"inlineHelpText":null,"label":"Last Referenced Date","length":0,"maskType":null,"nameField":false,"polymorphicForeignKey":false,"precision":0,"reference":false,"referenceTargetField":null,"referenceToInfos":[],"relationshipName":null,"required":false,"scale":0,"searchPrefilterable":false,"sortable":true,"unique":false,"updateable":false},"LastViewedDate":{"apiName":"LastViewedDate","calculated":false,"compound":false,"compoundComponentName":null,"compoundFieldName":null,"controllerName":null,"controllingFields":[],"createable":false,"custom":false,"dataType":"DateTime","externalId":false,"extraTypeInfo":null,"filterable":true,"filteredLookupInfo":null,"highScaleNumber":false,"htmlFormatted":false,"inlineHelpText":null,"label":"Last Viewed Date","length":0,"maskType":null,"nameField":false,"polymorphicForeignKey":false,"precision":0,"reference":false,"referenceTargetField":null,"referenceToInfos":[],"relationshipName":null,"required":false,"scale":0,"searchPrefilterable":false,"sortable":true,"unique":false,"updateable":false},"Name":{"apiName":"Name","calculated":false,"compound":false,"compoundComponentName":null,"compoundFieldName":null,"controllerName":null,"controllingFields":[],"createable":true,"custom":false,"dataType":"String","externalId":false,"extraTypeInfo":null,"filterable":true,"filteredLookupInfo":null,"highScaleNumber":false,"htmlFormatted":false,"inlineHelpText":null,"label":"Product Name","length":255,"maskType":null,"nameField":true,"polymorphicForeignKey":false,"precision":0,"reference":false,"referenceTargetField":null,"referenceToInfos":[],"relationshipName":null,"required":true,"scale":0,"searchPrefilterable":false,"sortable":true,"unique":false,"updateable":true},"ProductCode":{"apiName":"ProductCode","calculated":false,"compound":false,"compoundComponentName":null,"compoundFieldName":null,"controllerName":null,"controllingFields":[],"createable":true,"custom":false,"dataType":"String","externalId":false,"extraTypeInfo":null,"filterable":true,"filteredLookupInfo":null,"highScaleNumber":false,"htmlFormatted":false,"inlineHelpText":null,"label":"Product Code","length":255,"maskType":null,"nameField":false,"polymorphicForeignKey":false,"precision":0,"reference":false,"referenceTargetField":null,"referenceToInfos":[],"relationshipName":null,"required":false,"scale":0,"searchPrefilterable":false,"sortable":true,"unique":false,"updateable":true},"Product_Barcode__c":{"apiName":"Product_Barcode__c","calculated":false,"compound":false,"compoundComponentName":null,"compoundFieldName":null,"controllerName":null,"controllingFields":[],"createable":true,"custom":true,"dataType":"String","externalId":false,"extraTypeInfo":null,"filterable":true,"filteredLookupInfo":null,"highScaleNumber":false,"htmlFormatted":false,"inlineHelpText":null,"label":"Product Barcode","length":100,"maskType":null,"nameField":false,"polymorphicForeignKey":false,"precision":0,"reference":false,"referenceTargetField":null,"referenceToInfos":[],"relationshipName":null,"required":false,"scale":0,"searchPrefilterable":false,"sortable":true,"unique":false,"updateable":true},"QuantityUnitOfMeasure":{"apiName":"QuantityUnitOfMeasure","calculated":false,"compound":false,"compoundComponentName":null,"compoundFieldName":null,"controllerName":null,"controllingFields":[],"createable":true,"custom":false,"dataType":"Picklist","externalId":false,"extraTypeInfo":null,"filterable":true,"filteredLookupInfo":null,"highScaleNumber":false,"htmlFormatted":false,"inlineHelpText":null,"label":"Quantity Unit Of Measure","length":255,"maskType":null,"nameField":false,"polymorphicForeignKey":false,"precision":0,"reference":false,"referenceTargetField":null,"referenceToInfos":[],"relationshipName":null,"required":false,"scale":0,"searchPrefilterable":false,"sortable":true,"unique":false,"updateable":true},"StockKeepingUnit":{"apiName":"StockKeepingUnit","calculated":false,"compound":false,"compoundComponentName":null,"compoundFieldName":null,"controllerName":null,"controllingFields":[],"createable":true,"custom":false,"dataType":"String","externalId":false,"extraTypeInfo":null,"filterable":true,"filteredLookupInfo":null,"highScaleNumber":false,"htmlFormatted":false,"inlineHelpText":null,"label":"Product SKU","length":180,"maskType":null,"nameField":false,"polymorphicForeignKey":false,"precision":0,"reference":false,"referenceTargetField":null,"referenceToInfos":[],"relationshipName":null,"required":false,"scale":0,"searchPrefilterable":false,"sortable":true,"unique":false,"updateable":true},"SystemModstamp":{"apiName":"SystemModstamp","calculated":false,"compound":false,"compoundComponentName":null,"compoundFieldName":null,"controllerName":null,"controllingFields":[],"createable":false,"custom":false,"dataType":"DateTime","externalId":false,"extraTypeInfo":null,"filterable":true,"filteredLookupInfo":null,"highScaleNumber":false,"htmlFormatted":false,"inlineHelpText":null,"label":"System Modstamp","length":0,"maskType":null,"nameField":false,"polymorphicForeignKey":false,"precision":0,"reference":false,"referenceTargetField":null,"referenceToInfos":[],"relationshipName":null,"required":true,"scale":0,"searchPrefilterable":false,"sortable":true,"unique":false,"updateable":false}},"keyPrefix":"01t","label":"Product","labelPlural":"Products","layoutable":true,"mruEnabled":true,"nameFields":["Name"],"queryable":true,"recordTypeInfos":{"012000000000000AAA":{"available":true,"defaultRecordTypeMapping":true,"master":true,"name":"Master","recordTypeId":"012000000000000AAA"}},"searchLayoutable":true,"searchable":true,"themeInfo":{"color":"5A1BA9","iconUrl":"https://mfs-cs41.my.salesforce.com/img/icon/t4v35/standard/product_120.png"},"updateable":true}